videosdk/plugins/lmnt/__init__.py
videosdk/plugins/lmnt/tts.py
videosdk/plugins/lmnt/version.py
videosdk_plugins_lmnt-0.0.58.dist-info/METADATA
videosdk_plugins_lmnt-0.0.58.dist-info/WHEEL
videosdk_plugins_lmnt-0.0.58.dist-info/RECORD
