Metadata-Version: 2.4
Name: videosdk-plugins-lmnt
Version: 0.0.58
Summary: VideoSDK Agent Framework plugin for LMNT AI Text-to-Speech services
Author: videosdk
License-Expression: Apache-2.0
Keywords: ai,audio,lmnt,tts,video,videosdk
Classifier: Development Status :: 4 - Beta
Classifier: Intended Audience :: Developers
Classifier: Topic :: Communications :: Conferencing
Classifier: Topic :: Multimedia :: Sound/Audio
Classifier: Topic :: Multimedia :: Video
Classifier: Topic :: Scientific/Engineering :: Artificial Intelligence
Requires-Python: >=3.11
Requires-Dist: httpx>=0.24.0
Requires-Dist: videosdk-agents>=0.0.58
